orng/__init__.py
orng/_utils.py
orng/orng.py
orng/backends/__init__.py
orng/backends/cupy.py
orng/backends/jax.py
orng/backends/numpy.py
orng/backends/torch.py
orng-0.1.0a4.dist-info/licenses/LICENSE
orng-0.1.0a4.dist-info/METADATA
orng-0.1.0a4.dist-info/WHEEL
orng-0.1.0a4.dist-info/top_level.txt
orng-0.1.0a4.dist-info/RECORD
