Metadata-Version: 2.4
Name: orng
Version: 0.1.0a4
Summary: Omni RNG: A unified, cross-backend random number generator built on the Array API standard.
Author: Michael J. Williams, Christian Chapman-Bird
License: MIT License
Project-URL: Homepage, https://github.com/sequince-dev/orng
Project-URL: Repository, https://github.com/sequince-dev/orng
Requires-Python: >=3.10
License-File: LICENSE
Provides-Extra: numpy
Requires-Dist: numpy>=1.22; extra == "numpy"
Provides-Extra: torch
Requires-Dist: torch>=2.0; extra == "torch"
Provides-Extra: cupy
Requires-Dist: cupy>=12.0; extra == "cupy"
Provides-Extra: jax
Requires-Dist: jax>=0.4; extra == "jax"
Dynamic: license-file
